chord_progressions/__init__.py
chord_progressions/chord.py
chord_progressions/evaluate.py
chord_progressions/midi.py
chord_progressions/pitch.py
chord_progressions/progression.py
chord_progressions/type_templates.py
chord_progressions/utils.py
chord_progressions/extract/__init__.py
chord_progressions/extract/audio.py
chord_progressions/extract/midi.py
chord_progressions/extract/midi_harman.py
chord_progressions/io/__init__.py
chord_progressions/io/audio.py
chord_progressions/io/midi.py
chord_progressions-0.37.1.dist-info/LICENSE
chord_progressions-0.37.1.dist-info/METADATA
chord_progressions-0.37.1.dist-info/WHEEL
chord_progressions-0.37.1.dist-info/top_level.txt
chord_progressions-0.37.1.dist-info/RECORD
