Metadata-Version: 2.1
Name: chord-progressions
Version: 0.37.1
Summary: A Python package for working with chord progressions 
Author-email: p3zo <p3zo@users.noreply.github.com>
License: MIT License
Project-URL: Homepage, https://github.com/p3zo/chord-progressions
Project-URL: Issues, https://github.com/p3zo/chord-progressions/issues
Classifier: Programming Language :: Python :: 3
Classifier: License :: OSI Approved :: MIT License
Classifier: Operating System :: OS Independent
Classifier: Development Status :: 3 - Alpha
Requires-Python: >=3.9
License-File: LICENSE
Requires-Dist: matplotlib ~=3.5.1
Requires-Dist: mido ~=1.2.10
Requires-Dist: networkx ~=2.8
Requires-Dist: numpy ~=1.22.3
Requires-Dist: pandas ~=1.4.2
Requires-Dist: pretty-midi ~=0.2.10
Requires-Dist: scipy ~=1.8.0
Provides-Extra: dev
Requires-Dist: pytest ; extra == 'dev'
Requires-Dist: pytest-cov ; extra == 'dev'
Requires-Dist: black ; extra == 'dev'
Requires-Dist: flake8 ; extra == 'dev'
Requires-Dist: ipdb ; extra == 'dev'
Requires-Dist: ipython ; extra == 'dev'
Requires-Dist: isort ; extra == 'dev'
Requires-Dist: bump-my-version ; extra == 'dev'
Requires-Dist: mkdocs-material ; extra == 'dev'
Provides-Extra: test
Requires-Dist: pytest ; extra == 'test'
Requires-Dist: pytest-cov ; extra == 'test'
